beamxs/__init__.py
beamxs/beamxs.py
beamxs-1.1.1.dist-info/LICENSE
beamxs-1.1.1.dist-info/METADATA
beamxs-1.1.1.dist-info/WHEEL
beamxs-1.1.1.dist-info/top_level.txt
beamxs-1.1.1.dist-info/RECORD
